swiftpipeline/__init__.py
swiftpipeline/__version__.py
swiftpipeline/argumentparser.py
swiftpipeline/config.py
swiftpipeline/html.py
swiftpipeline/imageconfig.py
swiftpipeline/imaging.py
swiftpipeline/templates/base.html
swiftpipeline/templates/image_gallery.html
swiftpipeline/templates/image_halo.html
swiftpipeline/templates/mathjax.js
swiftpipeline/templates/plot_viewer.html
swiftpipeline/templates/polyfill.js
swiftpipeline/templates/style.css
swiftpipeline-0.3.5.data/scripts/swift-image
swiftpipeline-0.3.5.data/scripts/swift-pipeline
swiftpipeline-0.3.5.dist-info/LICENSE.md
swiftpipeline-0.3.5.dist-info/METADATA
swiftpipeline-0.3.5.dist-info/WHEEL
swiftpipeline-0.3.5.dist-info/top_level.txt
swiftpipeline-0.3.5.dist-info/RECORD
