Metadata-Version: 2.1
Name: swiftpipeline
Version: 0.3.5
Summary: Pipeline for producing galaxy scaling relation plots.
Home-page: https://github.com/SWIFTSIM/pipeline
Author: Josh Borrow
Author-email: josh@joshborrow.com
License: UNKNOWN
Platform: UNKNOWN
Classifier: Programming Language :: Python :: 3.6
Classifier: Programming Language :: Python :: 3.7
Classifier: Programming Language :: Python :: 3.8
Classifier: License :: OSI Approved :: GNU Lesser General Public License v3 or later (LGPLv3+)
Classifier: Operating System :: OS Independent
Requires-Dist: astropy
Requires-Dist: swiftsimio
Requires-Dist: matplotlib
Requires-Dist: jinja2
Requires-Dist: velociraptor
Requires-Dist: unyt
Requires-Dist: tqdm
Requires-Dist: p-tqdm
